{
  "id": 0,
  "name": "Sushi 14",
  "deliveryDay": null,
  "isPublic": true,
  "foodItems": [
    {
      "restaurantName": "Umamiya Sushi",
      "foodItems": [
        {
          "name": "Spicy Tuna Roll",
          "description": "Sushi roll with spicy tuna and cucumber",
          "quantity": 1,
          "price": 12.5,
          "imageUrl": "https://images.unsplash.com/photo-1553621042-f6e147245754?q=80&w=3125&auto=format&fit=crop&ixlib=rb-4.0.3&ixid=M3wxMjA3fDB8MHxwaG90by1wYWdlfHx8fGVufDB8fHx8fA%3D%3D",
          "dishId": 39
        }
      ]
    }
  ],
  "cost": "12.50"
}